setup.py
vaporize/__init__.py
vaporize/core.py
vaporize/databases.py
vaporize/domains.py
vaporize/exceptions.py
vaporize/loadbalancers.py
vaporize/nextgen_servers.py
vaporize/servers.py
vaporize/utils.py
vaporize/volumes.py
vaporize.egg-info/PKG-INFO
vaporize.egg-info/SOURCES.txt
vaporize.egg-info/dependency_links.txt
vaporize.egg-info/requires.txt
vaporize.egg-info/top_level.txt