Metadata-Version: 1.1
Name: vaporize
Version: 0.3.0
Summary: A clean and consistent library for the Rackspace Cloud / OpenStack
Home-page: https://github.com/kolanos/vaporize
Author: Michael Lavers
Author-email: kolanos@gmail.com
License: MIT
Keywords: rackspace openstack cloudservers cloudloadblancers clouddns
Platform: UNKNOWN
Classifier: Development Status :: 4 - Beta
Classifier: Environment :: Console
Classifier: Intended Audience :: Developers
Classifier: Intended Audience :: Information Technology
Classifier: License :: OSI Approved :: MIT License
Classifier: Operating System :: OS Independent
Classifier: Programming Language :: Python
Classifier: Topic :: Internet :: WWW/HTTP
Classifier: Topic :: Software Development :: Libraries :: Python Modules
Classifier: Topic :: System :: Distributed Computing
Classifier: Topic :: Utilities
